sendly/__init__.py
sendly/client.py
sendly/errors.py
sendly/types.py
sendly/webhooks.py
sendly/resources/__init__.py
sendly/resources/account.py
sendly/resources/messages.py
sendly/resources/templates.py
sendly/resources/verify.py
sendly/resources/webhooks.py
sendly/utils/__init__.py
sendly/utils/http.py
sendly/utils/validation.py
sendly-3.12.3.dist-info/METADATA
sendly-3.12.3.dist-info/WHEEL
sendly-3.12.3.dist-info/RECORD
