Metadata-Version: 2.4
Name: sendly
Version: 3.12.3
Summary: Official Sendly Python SDK for SMS messaging
Project-URL: Homepage, https://sendly.live
Project-URL: Documentation, https://sendly.live/docs
Project-URL: Repository, https://github.com/SendlyHQ/sendly-python
Project-URL: Issues, https://github.com/SendlyHQ/sendly-python/issues
Author-email: Sendly <support@sendly.live>
License-Expression: MIT
Keywords: api,messaging,notifications,sendly,sms,text
Classifier: Development Status :: 5 - Production/Stable
Classifier: Intended Audience :: Developers
Classifier: License :: OSI Approved :: MIT License
Classifier: Operating System :: OS Independent
Classifier: Programming Language :: Python :: 3
Classifier: Programming Language :: Python :: 3.8
Classifier: Programming Language :: Python :: 3.9
Classifier: Programming Language :: Python :: 3.10
Classifier: Programming Language :: Python :: 3.11
Classifier: Programming Language :: Python :: 3.12
Classifier: Topic :: Communications :: Telephony
Classifier: Topic :: Software Development :: Libraries :: Python Modules
Classifier: Typing :: Typed
Requires-Python: >=3.8
Requires-Dist: httpx>=0.25.0
Requires-Dist: pydantic>=2.0.0
Provides-Extra: dev
Requires-Dist: mypy>=1.0.0; extra == 'dev'
Requires-Dist: pytest-asyncio>=0.21.0; extra == 'dev'
Requires-Dist: pytest-httpx>=0.22.0; extra == 'dev'
Requires-Dist: pytest>=7.0.0; extra == 'dev'
Requires-Dist: ruff>=0.1.0; extra == 'dev'
